{
    "target_date": "2026-04-27",
    "last_updated": "2026-04-26T22:37:21.733698+00:00",
    "projection_system": "STEAMER",
    "total_efficiency_score": 530.1,
    "narrative": "AI Narrative generation skipped.",
    "recommended_lineup": [
        {
            "Slot": "C1",
            "Player": "Dalton Rushing",
            "POS": "C",
            "Score": 57.785065598859525,
            "Breakdown": [
                {
                    "label": "Lineup Pending (Assumed #7)",
                    "value": null,
                    "type": "info"
                },
                {
                    "label": "Base",
                    "value": "48.03",
                    "type": "info"
                },
                {
                    "label": "SP Skill",
                    "value": "+15%",
                    "type": "positive"
                },
                {
                    "label": "Platoon",
                    "value": "+7%",
                    "type": "positive"
                },
                {
                    "label": "Order #7",
                    "value": "-3%",
                    "type": "negative"
                }
            ],
            "Opponent": "Chris Paddack (R)",
            "SP_xERA": "4.64",
            "Warning": "",
            "GameTime": "2026-04-28T02:10:00Z",
            "Order": "7*",
            "Start": "02:10 AM"
        },
        {
            "Slot": "C2",
            "Player": "Luis Campusano",
            "POS": "C",
            "Score": 48.961212092389154,
            "Breakdown": [
                {
                    "label": "Lineup Pending (Assumed #8)",
                    "value": null,
                    "type": "info"
                },
                {
                    "label": "Base",
                    "value": "48.59",
                    "type": "info"
                },
                {
                    "label": "Park",
                    "value": "-2%",
                    "type": "negative"
                },
                {
                    "label": "SP Skill",
                    "value": "+2%",
                    "type": "positive"
                },
                {
                    "label": "Platoon",
                    "value": "+7%",
                    "type": "positive"
                },
                {
                    "label": "Order #8",
                    "value": "-6%",
                    "type": "negative"
                }
            ],
            "Opponent": "Matthew Boyd (L)",
            "SP_xERA": "4.09",
            "Warning": "",
            "GameTime": "2026-04-28T01:40:00Z",
            "Order": "8*",
            "Start": "01:40 AM"
        },
        {
            "Slot": "1B",
            "Player": "Josh Naylor",
            "POS": "1B",
            "Score": 65.72028750973467,
            "Breakdown": [
                {
                    "label": "Lineup Pending (Assumed #4)",
                    "value": null,
                    "type": "info"
                },
                {
                    "label": "Base",
                    "value": "58.12",
                    "type": "info"
                },
                {
                    "label": "Park",
                    "value": "+2%",
                    "type": "positive"
                },
                {
                    "label": "SP Skill",
                    "value": "+12%",
                    "type": "positive"
                },
                {
                    "label": "Dynamic Platoon (L)",
                    "value": "-5%",
                    "type": "negative"
                },
                {
                    "label": "Order #4",
                    "value": "+4%",
                    "type": "positive"
                }
            ],
            "Opponent": "Connor Prielipp (L)",
            "SP_xERA": "4.50",
            "Warning": "",
            "GameTime": "2026-04-27T23:40:00Z",
            "Order": "4*",
            "Start": "11:40 PM"
        },
        {
            "Slot": "2B",
            "Player": "Jazz Chisholm Jr.",
            "POS": "2B/3B",
            "Score": 73.6247715635272,
            "Breakdown": [
                {
                    "label": "Lineup Pending (Assumed #5)",
                    "value": null,
                    "type": "info"
                },
                {
                    "label": "Base",
                    "value": "59.66",
                    "type": "info"
                },
                {
                    "label": "SP Skill",
                    "value": "+10%",
                    "type": "positive"
                },
                {
                    "label": "Dynamic Platoon (R)",
                    "value": "+7%",
                    "type": "positive"
                },
                {
                    "label": "Slow SP Delivery (94% SB)",
                    "value": "+2%",
                    "type": "positive"
                },
                {
                    "label": "Order #5",
                    "value": "+2%",
                    "type": "positive"
                }
            ],
            "Opponent": "Jack Leiter (R)",
            "SP_xERA": "4.43",
            "Warning": "",
            "GameTime": "2026-04-28T00:05:00Z",
            "Order": "5*",
            "Start": "12:05 AM"
        },
        {
            "Slot": "SS",
            "Player": "Trevor Story",
            "POS": "SS",
            "Score": 54.84146300034564,
            "Breakdown": [
                {
                    "label": "Lineup Pending (Assumed #4)",
                    "value": null,
                    "type": "info"
                },
                {
                    "label": "Base",
                    "value": "54.68",
                    "type": "info"
                },
                {
                    "label": "Park",
                    "value": "+3%",
                    "type": "positive"
                },
                {
                    "label": "SP Skill",
                    "value": "-10%",
                    "type": "negative"
                },
                {
                    "label": "Neutral Platoon (R)",
                    "value": null,
                    "type": "info"
                },
                {
                    "label": "Slow SP Delivery (88% SB)",
                    "value": "+4%",
                    "type": "positive"
                },
                {
                    "label": "Order #4",
                    "value": "+4%",
                    "type": "positive"
                }
            ],
            "Opponent": "Dylan Cease (R)",
            "SP_xERA": "3.58",
            "Warning": "",
            "GameTime": "2026-04-27T23:07:00Z",
            "Order": "4*",
            "Start": "11:07 PM"
        },
        {
            "Slot": "3B",
            "Player": "Alex Freeland",
            "POS": "2B/SS/3B",
            "Score": 51.939206353801445,
            "Breakdown": [
                {
                    "label": "Lineup Pending (Assumed #9)",
                    "value": null,
                    "type": "info"
                },
                {
                    "label": "Base",
                    "value": "47.81",
                    "type": "info"
                },
                {
                    "label": "SP Skill",
                    "value": "+15%",
                    "type": "positive"
                },
                {
                    "label": "Switch",
                    "value": "+3%",
                    "type": "positive"
                },
                {
                    "label": "Order #9",
                    "value": "-8%",
                    "type": "negative"
                }
            ],
            "Opponent": "Chris Paddack (R)",
            "SP_xERA": "4.64",
            "Warning": "",
            "GameTime": "2026-04-28T02:10:00Z",
            "Order": "9*",
            "Start": "02:10 AM"
        },
        {
            "Slot": "OF3",
            "Player": "Giancarlo Stanton",
            "POS": "OF",
            "Score": 61.90540328625584,
            "Breakdown": [
                {
                    "label": "Lineup Pending (Assumed #5)",
                    "value": null,
                    "type": "info"
                },
                {
                    "label": "Base",
                    "value": "55.05",
                    "type": "info"
                },
                {
                    "label": "SP Skill",
                    "value": "+10%",
                    "type": "positive"
                },
                {
                    "label": "Neutral Platoon (R)",
                    "value": null,
                    "type": "info"
                },
                {
                    "label": "Order #5",
                    "value": "+2%",
                    "type": "positive"
                }
            ],
            "Opponent": "Jack Leiter (R)",
            "SP_xERA": "4.43",
            "Warning": "",
            "GameTime": "2026-04-28T00:05:00Z",
            "Order": "5*",
            "Start": "12:05 AM"
        },
        {
            "Slot": "OF5",
            "Player": "Jose Caballero",
            "POS": "2B/SS/3B/OF",
            "Score": 50.136840761592076,
            "Breakdown": [
                {
                    "label": "Lineup Pending (Assumed #9)",
                    "value": null,
                    "type": "info"
                },
                {
                    "label": "Base",
                    "value": "56.17",
                    "type": "info"
                },
                {
                    "label": "SP Skill",
                    "value": "+10%",
                    "type": "positive"
                },
                {
                    "label": "Dynamic Platoon (R)",
                    "value": "-13%",
                    "type": "negative"
                },
                {
                    "label": "Slow SP Delivery (94% SB)",
                    "value": "+2%",
                    "type": "positive"
                },
                {
                    "label": "Order #9",
                    "value": "-8%",
                    "type": "negative"
                }
            ],
            "Opponent": "Jack Leiter (R)",
            "SP_xERA": "4.43",
            "Warning": "",
            "GameTime": "2026-04-28T00:05:00Z",
            "Order": "9*",
            "Start": "12:05 AM"
        },
        {
            "Slot": "UTIL",
            "Player": "Seiya Suzuki",
            "POS": "OF",
            "Score": 65.1819992779431,
            "Breakdown": [
                {
                    "label": "Lineup Pending (Assumed #4)",
                    "value": null,
                    "type": "info"
                },
                {
                    "label": "Base",
                    "value": "54.74",
                    "type": "info"
                },
                {
                    "label": "Park",
                    "value": "-2%",
                    "type": "negative"
                },
                {
                    "label": "SP Skill",
                    "value": "+19%",
                    "type": "positive"
                },
                {
                    "label": "Dynamic Platoon (R)",
                    "value": "-2%",
                    "type": "negative"
                },
                {
                    "label": "Order #4",
                    "value": "+4%",
                    "type": "positive"
                }
            ],
            "Opponent": "Randy V\u00e1squez (R)",
            "SP_xERA": "5.43",
            "Warning": "",
            "GameTime": "2026-04-28T01:40:00Z",
            "Order": "4*",
            "Start": "01:40 AM"
        }
    ],
    "players_sat": [
        {
            "Slot": "BN",
            "Player": "Corbin Carroll",
            "POS": "OF",
            "Order": "-",
            "Start": "-",
            "Opponent": "N/A",
            "SP_xERA": "-",
            "Score": 0.0,
            "Breakdown": [
                {
                    "label": "Team Off-day or No Game Scheduled.",
                    "value": null,
                    "type": "info"
                }
            ],
            "Warning": "",
            "GameTime": null
        },
        {
            "Slot": "BN",
            "Player": "James Wood",
            "POS": "OF",
            "Order": "-",
            "Start": "-",
            "Opponent": "N/A",
            "SP_xERA": "-",
            "Score": 0.0,
            "Breakdown": [
                {
                    "label": "Team Off-day or No Game Scheduled.",
                    "value": null,
                    "type": "info"
                }
            ],
            "Warning": "",
            "GameTime": null
        },
        {
            "Slot": "BN",
            "Player": "Tyler Soderstrom",
            "POS": "1B/OF",
            "Order": "-",
            "Start": "-",
            "Opponent": "N/A",
            "SP_xERA": "-",
            "Score": 0.0,
            "Breakdown": [
                {
                    "label": "Team Off-day or No Game Scheduled.",
                    "value": null,
                    "type": "info"
                }
            ],
            "Warning": "",
            "GameTime": null
        },
        {
            "Slot": "BN",
            "Player": "Vinnie Pasquantino",
            "POS": "1B",
            "Order": "-",
            "Start": "-",
            "Opponent": "N/A",
            "SP_xERA": "-",
            "Score": 0.0,
            "Breakdown": [
                {
                    "label": "Team Off-day or No Game Scheduled.",
                    "value": null,
                    "type": "info"
                }
            ],
            "Warning": "",
            "GameTime": null
        },
        {
            "Slot": "BN",
            "Player": "Mickey Moniak",
            "POS": "OF",
            "Order": "-",
            "Start": "-",
            "Opponent": "N/A",
            "SP_xERA": "-",
            "Score": 0.0,
            "Breakdown": [
                {
                    "label": "Team Off-day or No Game Scheduled.",
                    "value": null,
                    "type": "info"
                }
            ],
            "Warning": "",
            "GameTime": null
        },
        {
            "Slot": "BN",
            "Player": "Austin Riley",
            "POS": "3B",
            "Order": "-",
            "Start": "-",
            "Opponent": "N/A",
            "SP_xERA": "-",
            "Score": 0.0,
            "Breakdown": [
                {
                    "label": "Team Off-day or No Game Scheduled.",
                    "value": null,
                    "type": "info"
                }
            ],
            "Warning": "",
            "GameTime": null
        },
        {
            "Slot": "BN",
            "Player": "Brice Turang",
            "POS": "2B",
            "Order": "-",
            "Start": "-",
            "Opponent": "N/A",
            "SP_xERA": "-",
            "Score": 0.0,
            "Breakdown": [
                {
                    "label": "Team Off-day or No Game Scheduled.",
                    "value": null,
                    "type": "info"
                }
            ],
            "Warning": "",
            "GameTime": null
        },
        {
            "Slot": "BN",
            "Player": "Gabriel Moreno",
            "POS": "C",
            "Order": "-",
            "Start": "-",
            "Opponent": "N/A",
            "SP_xERA": "-",
            "Score": 0.0,
            "Breakdown": [
                {
                    "label": "IL (Injured)",
                    "value": null,
                    "type": "status"
                },
                {
                    "label": "Injured (IL) - Not available.",
                    "value": null,
                    "type": "info"
                }
            ],
            "Warning": "\ud83d\udea8 INJURED (IL)",
            "GameTime": null
        },
        {
            "Slot": "BN",
            "Player": "Max Muncy",
            "POS": "2B/SS/3B",
            "Order": "-",
            "Start": "-",
            "Opponent": "N/A",
            "SP_xERA": "-",
            "Score": 0.0,
            "Breakdown": [
                {
                    "label": "Team Off-day or No Game Scheduled.",
                    "value": null,
                    "type": "info"
                }
            ],
            "Warning": "",
            "GameTime": null
        },
        {
            "Slot": "BN",
            "Player": "Zach McKinstry",
            "POS": "2B/SS/3B/OF",
            "Order": "-",
            "Start": "-",
            "Opponent": "N/A",
            "SP_xERA": "-",
            "Score": 0.0,
            "Breakdown": [
                {
                    "label": "IL (Injured)",
                    "value": null,
                    "type": "status"
                },
                {
                    "label": "Injured (IL) - Not available.",
                    "value": null,
                    "type": "info"
                }
            ],
            "Warning": "\ud83d\udea8 INJURED (IL)",
            "GameTime": null
        },
        {
            "Slot": "BN",
            "Player": "Kyle Karros",
            "POS": "3B",
            "Order": "-",
            "Start": "-",
            "Opponent": "N/A",
            "SP_xERA": "-",
            "Score": 0.0,
            "Breakdown": [
                {
                    "label": "Team Off-day or No Game Scheduled.",
                    "value": null,
                    "type": "info"
                }
            ],
            "Warning": "",
            "GameTime": null
        },
        {
            "Slot": "BN",
            "Player": "Carson Williams",
            "POS": "SS",
            "Order": "-",
            "Start": "-",
            "Opponent": "N/A",
            "SP_xERA": "-",
            "Score": 0.0,
            "Breakdown": [
                {
                    "label": "In the Minors (Durham Bulls)",
                    "value": null,
                    "type": "status"
                },
                {
                    "label": "In the Minors (Not on Active Roster).",
                    "value": null,
                    "type": "info"
                }
            ],
            "Warning": "\ud83d\udea8 MINORS",
            "GameTime": null
        },
        {
            "Slot": "BN",
            "Player": "Travis Bazzana",
            "POS": "2B",
            "Order": "-",
            "Start": "-",
            "Opponent": "N/A",
            "SP_xERA": "-",
            "Score": 0.0,
            "Breakdown": [
                {
                    "label": "In the Minors (Columbus Clippers)",
                    "value": null,
                    "type": "status"
                },
                {
                    "label": "In the Minors (Not on Active Roster).",
                    "value": null,
                    "type": "info"
                }
            ],
            "Warning": "\ud83d\udea8 MINORS",
            "GameTime": null
        }
    ]
}